acctext/__init__.py
acctext/core.py
acctext/graphql.py
acctext/transforms.py
acctext-0.9.2.dist-info/LICENCE
acctext-0.9.2.dist-info/METADATA
acctext-0.9.2.dist-info/WHEEL
acctext-0.9.2.dist-info/top_level.txt
acctext-0.9.2.dist-info/RECORD
