Metadata-Version: 2.1
Name: acctext
Version: 0.9.2
Summary: Python wrapper for Accelerated Text
Home-page: https://github.com/tokenmill/accelerated-text-py/
Author: Rokas Ramanauskas
Author-email: rokas.ramanauskas@tokenmill.lt
License: UNKNOWN
Project-URL: Accelerated Text, https://github.com/tokenmill/accelerated-text/
Platform: UNKNOWN
Classifier: Programming Language :: Python :: 3
Classifier: License :: OSI Approved :: Apache Software License
Classifier: Operating System :: OS Independent
Requires-Python: >=3.6
License-File: LICENCE
Requires-Dist: requests
Requires-Dist: edn-format
